com/__init__.py
com/vmware/__init__.py
com/vmware/appliance_client.py
com/vmware/cis_client.py
com/vmware/content_client.py
com/vmware/oauth2_client.py
com/vmware/vapi_client.py
com/vmware/vcenter_client.py
com/vmware/vstats_client.py
com/vmware/appliance/__init__.py
com/vmware/appliance/access_client.py
com/vmware/appliance/health_client.py
com/vmware/appliance/infraprofile_client.py
com/vmware/appliance/local_accounts_client.py
com/vmware/appliance/localaccounts_client.py
com/vmware/appliance/logging_client.py
com/vmware/appliance/monitoring_client.py
com/vmware/appliance/networking_client.py
com/vmware/appliance/ntp_client.py
com/vmware/appliance/recovery_client.py
com/vmware/appliance/shutdown_client.py
com/vmware/appliance/support_bundle_client.py
com/vmware/appliance/supportbundle_client.py
com/vmware/appliance/system_client.py
com/vmware/appliance/update_client.py
com/vmware/appliance/vmon_client.py
com/vmware/appliance/networking/__init__.py
com/vmware/appliance/networking/dns_client.py
com/vmware/appliance/networking/firewall_client.py
com/vmware/appliance/networking/interfaces_client.py
com/vmware/appliance/recovery/__init__.py
com/vmware/appliance/recovery/backup_client.py
com/vmware/appliance/recovery/reconciliation_client.py
com/vmware/appliance/recovery/restore_client.py
com/vmware/appliance/recovery/backup/__init__.py
com/vmware/appliance/recovery/backup/job_client.py
com/vmware/appliance/recovery/backup/system_name_client.py
com/vmware/appliance/system/__init__.py
com/vmware/appliance/system/security_client.py
com/vmware/appliance/system/time_client.py
com/vmware/appliance/vcenter/__init__.py
com/vmware/appliance/vcenter/settings/__init__.py
com/vmware/appliance/vcenter/settings/v1_client.py
com/vmware/appliance/vcenter/settings/v1/__init__.py
com/vmware/appliance/vcenter/settings/v1/config_client.py
com/vmware/appliance/vcenter/settings/v1/config/__init__.py
com/vmware/appliance/vcenter/settings/v1/config/components_client.py
uc_vcenter_bindings-4.2.1.dist-info/licenses/LICENSE
uc_vcenter_bindings-4.2.1.dist-info/METADATA
uc_vcenter_bindings-4.2.1.dist-info/WHEEL
uc_vcenter_bindings-4.2.1.dist-info/top_level.txt
uc_vcenter_bindings-4.2.1.dist-info/RECORD
